record_shelf/__init__.py
record_shelf/cli.py
record_shelf/config.py
record_shelf/py.typed
record_shelf/report_generator.py
record_shelf/utils.py
record_shelf-1.0.0.dist-info/licenses/LICENSE
record_shelf-1.0.0.dist-info/METADATA
record_shelf-1.0.0.dist-info/WHEEL
record_shelf-1.0.0.dist-info/entry_points.txt
record_shelf-1.0.0.dist-info/top_level.txt
record_shelf-1.0.0.dist-info/RECORD
