Metadata-Version: 2.4
Name: record-shelf
Version: 1.0.0
Summary: A tool for creating custom reports from music collection data
Home-page: https://github.com/bryankemp/record-shelf
Author: Bryan Kemp
Author-email: Bryan Kemp <bryan@kempville.com>
Project-URL: Homepage, https://github.com/bryankemp/record-shelf
Project-URL: Bug Reports, https://github.com/bryankemp/record-shelf/issues
Project-URL: Source, https://github.com/bryankemp/record-shelf
Project-URL: Documentation, https://record-shelf.readthedocs.io/
Project-URL: Changelog, https://github.com/bryankemp/record-shelf/blob/main/CHANGELOG.md
Keywords: discogs,music,collection,report,excel,csv
Classifier: Development Status :: 4 - Beta
Classifier: Intended Audience :: End Users/Desktop
Classifier: License :: OSI Approved :: MIT License
Classifier: Operating System :: OS Independent
Classifier: Programming Language :: Python :: 3
Classifier: Programming Language :: Python :: 3.8
Classifier: Programming Language :: Python :: 3.9
Classifier: Programming Language :: Python :: 3.10
Classifier: Programming Language :: Python :: 3.11
Classifier: Topic :: Multimedia :: Sound/Audio
Classifier: Topic :: Office/Business
Requires-Python: >=3.8
License-File: LICENSE
Requires-Dist: requests>=2.31.0
Requires-Dist: pandas>=2.0.0
Requires-Dist: openpyxl>=3.1.0
Requires-Dist: discogs-client>=2.3.0
Requires-Dist: click>=8.1.0
Requires-Dist: tqdm>=4.65.0
Provides-Extra: dev
Requires-Dist: pytest>=7.0.0; extra == "dev"
Requires-Dist: pytest-cov>=4.0.0; extra == "dev"
Requires-Dist: pylint>=2.15.0; extra == "dev"
Requires-Dist: black>=22.0.0; extra == "dev"
Requires-Dist: isort>=5.10.0; extra == "dev"
Requires-Dist: mypy>=1.0.0; extra == "dev"
Requires-Dist: tox>=4.0.0; extra == "dev"
Requires-Dist: build>=0.8.0; extra == "dev"
Requires-Dist: twine>=4.0.0; extra == "dev"
Requires-Dist: sphinx>=8.0.0; extra == "dev"
Requires-Dist: sphinx-rtd-theme>=3.0.0; extra == "dev"
Requires-Dist: sphinx-autodoc-typehints>=3.0.0; extra == "dev"
Requires-Dist: sphinx-click>=6.0.0; extra == "dev"
Provides-Extra: test
Requires-Dist: pytest>=7.0.0; extra == "test"
Requires-Dist: pytest-cov>=4.0.0; extra == "test"
Dynamic: author
Dynamic: home-page
Dynamic: license-file
Dynamic: requires-python
